Workbook

Sheet Novembre2025
A1: Date | B1: Montant | C1: Type de dépense | D1: Libellé | F1: Budget restant | G1: Budget initial
B2: -395 | C2: Logement | D2: Loyer | F2: =G2+SUM(B2:B200) -> 793.68 | G2: 420
A3: 45957 | B3: 1073.5 | C3: Revenu | D3: Salaire alternance
A4: 45962 | B4: -4.76 | C4: Transport | D4: Parking
A5: 45963 | B5: -49.37 | C5: Alimentation | D5: Courses
A6: 45963 | B6: -1.9 | C6: Alimentation | D6: Café
A7: 45964 | B7: -9.09 | C7: Loisirs | D7: Cinéma
A8: 45964 | B8: -21.16 | C8: Loisirs | D8: Livre
A9: 45965 | B9: -1.6 | C9: Alimentation | D9: Café
A10: 45965 | B10: -2.2 | C10: Alimentation | D10: Café
A11: 45966 | B11: 182 | C11: Revenu | D11: APL
A12: 45966 | B12: -1.79 | C12: Transport | D12: ticket bus
A13: 45967 | B13: -63.58 | C13: Alimentation | D13: Courses
A14: 45967 | B14: -1.8 | C14: Alimentation | D14: Café
A15: 45968 | B15: -1.8 | C15: Alimentation | D15: Café
A16: 45969 | B16: -24.99 | C16: Logement | D16: Internet box | O16: Prix café : | P16: =ABS(SUMIF(D2:D200,"Café",B2:B200)) -> 22.5
A17: 45969 | B17: -1.87 | C17: Alimentation | D17: Boulangerie
A18: 45969 | B18: -9.78 | C18: Loisirs | D18: Cinéma
A19: 45970 | B19: -10.99 | C19: Loisirs | D19: Cinéma
A20: 45970 | B20: -12.86 | C20: Transport | D20: Train
A21: 45970 | B21: -15.51 | C21: Loisirs | D21: Livre
A22: 45971 | B22: -30.44 | C22: Alimentation | D22: Courses
A23: 45971 | B23: -1.6 | C23: Alimentation | D23: Cafe
A24: 45972 | B24: -5.11 | C24: Alimentation | D24: Boulangerie
A25: 45972 | B25: -2.4 | C25: Alimentation | D25: Café
A26: 45973 | B26: -36.13 | C26: Logement | D26: Électricité
A27: 45973 | B27: -2.4 | C27: Alimentation | D27: Café
A28: 45973 | B28: -1.75 | C28: Transport | D28: Ticket bus
... A51: 45989 | B51: -8.25 | C51: Loisirs | D51: Cinéma

Sheet Decembre2025
A1: Date | B1: Montant | C1: Type de dépense | D1: Libellé | F1: Budget restant | G1: Budget initial
B2: -395 | C2: Logement | D2: Loyer | F2: =G2+SUM(B2:B200) -> 1342.61 | G2: =Novembre2025!F2 -> 793.68
A3: sans date | B3: -10.99 | C3: Loisirs | D3: Abonnement musique
A4: 45989 | B4: 1092 | C4: Revenu | D4: Salaire alternance
A5: 45993 | B5: -2.3 | C5: Alimentation | D5: Café
A6: 45994 | B6: -2 | C6: Alimentation | D6: Café
A7: 45994 | B7: -2.7 | C7: Alimentation | D7: Café
A8: 45995 | B8: 150 | C8: Revenu | D8: Prime de fin d'année
A9: 45995 | B9: -1.79 | C9: Transport | D9: Ticket bus
A10: 45995 | B10: -25.63 | C10: Transport | D10: Train
A11: 45996 | B11: 182 | C11: Revenu | D11: APL
A12: 45996 | B12: -24.54 | C12: Loisirs | D12: Restaurant
A13: 45997 | B13: -5.37 | C13: Alimentation | D13: Boulangerie
A14: 45998 | B14: -2.7 | C14: Alimentation | D14: CAFÉ
A15: 45998 | B15: -4.44 | C15: Alimentation | D15: Boulangerie
... A53: 46018 | B53: -2.6 | C53: Alimentation | D53: CAFÉ

Sheet Janvier2026
A1: Date | B1: Montant | C1: Type de dépense | D1: Libellé | F1: Budget restant | G1: Budget initial
B2: -395 | C2: Logement | D2: Loyer | F2: =G2+SUM(B2:B200) -> 1576.3 | G2: =Decembre2025!F2 -> 1342.61
A3: sans date | B3: -10.99 | C3: Loisirs | D3: Abonnement musique
A4: 45663 | B4: -3.45 | C4: Alimentation | D4: Boulangerie
A5: 46017 | B5: 1114 | C5: Revenu | D5: Salaire alternance
A6: 46023 | B6: -50.14 | C6: Alimentation | D6: Courses
A7: 46023 | B7: -50.04 | C7: Transport | D7: Essence
A8: 46024 | B8: -23.72 | C8: Alimentation | D8: Marché
A9: 46026 | B9: -16.07 | C9: Alimentation | D9: Marché
A10: 46026 | B10: -2.8 | C10: Alimentation | D10: Café
A11: 46026 | B11: -50.32 | C11: Alimentation | D11: Courses
A12: 46027 | B12: 182 | C12: Revenu | D12: APL
A13: 46027 | B13: -9.26 | C13: Loisirs | D13: Escalade
A14: 46028 | B14: 23.4 | C14: Revenu | D14: Remboursement mutuelle
A15: 46028 | B15: -14.09 | C15: Alimentation | D15: Courses
... A51: 46050 | B51: -37.23 | C51: Alimentation | D51: Courses

Sheet Fevrier2026
A1: Date | B1: Montant | C1: Type de dépense | D1: Libellé | F1: Budget restant | G1: Budget initial
B2: -395 | C2: Logement | D2: Loyer | F2: =G2+SUM(B2:B200) -> 1857.81 | G2: =Janvier2026!F2 -> 1576.3
A3: sans date | B3: -10.99 | C3: Loisirs | D3: Abonnement musique
A4: 46050 | B4: 1084.5 | C4: Revenu | D4: Salaire alternance
A5: 46054 | B5: -2.3 | C5: Alimentation | D5: Café
A6: 46055 | B6: -5.81 | C6: Alimentation | D6: Boulangerie
A7: 46055 | B7: -11.68 | C7: Loisirs | D7: Escalade
A8: 46055 | B8: -10.93 | C8: Loisirs | D8: Cinéma
A9: 46056 | B9: -27.47 | C9: Loisirs | D9: Restaurant
A10: 46057 | B10: -51.17 | C10: Alimentation | D10: Courses
A11: 46057 | B11: -36.1 | C11: Transport | D11: Essence
A12: 46058 | B12: 182 | C12: Revenu | D12: APL
A13: 46058 | B13: -10.16 | C13: Loisirs | D13: Cinéma
A14: 46058 | B14: -22.5 | C14: Alimentation | D14: Courses
A15: 46058 | B15: -4.19 | C15: Alimentation | D15: Boulangerie
... A28: 46066 | B28: -2.8 | C28: Alimentation | D28: Café
A29: 46067 | B29: =-12.5-7.3 -> -19.8 | C29: Alimentation | D29: Courses
A30: 14/02/2026 | B30: -23.5 | C30: Loisirs | D30: Restaurant
A31: 46067 | B31: -2.72 | C31: Alimentation | D31: Boulangerie
A32: 46067 | B32: -1.2 | C32: Alimentation | D32: Café
A33: 46069 | B33: -10.03 | C33: Loisirs | D33: Escalade
A34: 46070 | B34: -3.85 | C34: Alimentation | D34: Boulangerie
A35: 46070 | B35: -47.02 | C35: Alimentation | D35: Courses
A36: 46072 | B36: -63.93 | C36: Alimentation | D36: Courses
A37: 46072 | B37: -36.73 | C37: Alimentation | D37: Courses
A38: 46073 | B38: -1.5 | C38: Alimentation | D38: Café
A39: 46073 | B39: -3.2 | C39: Alimentation | D39: Boulangerie
A40: 21/02/2026 | B40: -1.8 | C40: Transport | D40: Ticket bus
A41: 46074 | B41: -2.55 | C41: Alimentation | D41: Boulangerie
A42: 46078 | B42: -2.3 | C42: Alimentation | D42: Cafe
A43: 46078 | B43: -12.47 | C43: Loisirs | D43: Escalade
A44: 46079 | B44: -2.5 | C44: Alimentation | D44: Café
A45: 46080 | B45: -5.34 | C45: Alimentation | D45: Boulangerie
A46: 46081 | B46: -5.99 | C46: Alimentation | D46: Boulangerie

Sheet Mars2026
A1: Date | B1: Montant | C1: Type de Depense | D1: Libelle | F1: Budget restant | G1: Budget initial
B2: -395 | C2: Logement | D2: Loyer | F2: =G2+SUM(B2:B200) -> 1769.75 | G2: =Fevrier2026!F2 -> 1857.81
A3: 46081 | B3: 1076.5 | C3: Revenu | D3: Salaire alternance
A4: 46082 | B4: -1.75 | C4: Transport | D4: Ticket Bus
A5: 46082 | B5: -1.3 | C5: Alimentation | D5: Café
A6: 46083 | B6: 96 | C6: Revenu | D6: Job week-end
A7: 46083 | B7: -18.94 | C7: Transport | D7: Train
A8: 46083 | B8: -6.04 | C8: Alimentation | D8: Boulangerie
A9: 46083 | B9: -2.85 | C9: Alimentation | D9: Boulangerie
A10: 46084 | B10: -1.7 | C10: Alimentation | D10: café
A11: 46084 | B11: -12.52 | C11: Alimentation | D11: Courses
A12: 46086 | B12: 182 | C12: Revenu | D12: APL
A13: 46086 | B13: -33.41 | C13: Alimentation | D13: Courses
A14: 46086 | B14: -61.66 | C14: Alimentation | D14: Courses
... A51: 46098 | B51: -3.06 | C51: Alimentation | D51: Boulangerie
A52: 46099 | B52: -(1,2+1,2) | C52: Alimentation | D52: Café
A53: 46099 | B53: -1.1 | C53: Alimentation | D53: Café
A54: 46099 | B54: -31.64 | C54: Transport | D54: Essence
A55: 46099 | B55: -30.8 | C55: Transport | D55: Essence
A56: 46100 | B56: -2.2 | C56: Alimentation | D56: Café
A57: 46100 | B57: -2.7 | C57: Alimentation | D57: Café
A58: 46100 | B58: -2.23 | C58: Alimentation | D58: Boulangerie
A59: 46101 | B59: 18 | C59: Transport | D59: Remboursement billet train
A60: 46101 | B60: -1.4 | C60: Alimentation | D60: Café
A61: 46101 | B61: -2.5 | C61: Alimentation | D61: Café
A62: 46103 | B62: -9.38 | C62: Loisirs | D62: Cinéma
A63: 46104 | B63: -6.26 | C63: Transport | D63: Parking
A64: 46104 | B64: -11.92 | C64: Loisirs | D64: Livre
... A79: 46109 | B79: -7.1 | C79: Transport | D79: Parking

Sheet Avril2026
A1: Date | B1: Montant | C1: Type de Depense | D1: Libelle | F1: Budget restant | G1: Budget initial
B2: -395 | C2: Logement | D2: Loyer | F2: =G2+SUM(B2:B200) -> 1861.04 | G2: =Mars2026!F2 -> 1769.75
A3: 46107 | B3: 1043.5 | C3: Revenu | D3: Salaire alternance
A4: 46113 | B4: -44.46 | C4: Alimentation | D4: Courses
A5: 46114 | B5: -31.13 | C5: Alimentation | D5: Courses
A6: 46115 | B6: -32.37 | C6: Transport | D6: Essence
A7: 46116 | B7: -21.81 | C7: Loisirs | D7: Restaurant
A8: 46116 | B8: -1.6 | C8: Alimentation | D8: Café
A9: 46116 | B9: -2.3 | C9: Alimentation | D9: Café
A10: 46117 | B10: 182 | C10: Revenu | D10: APL
A11: 46117 | B11: -2.57 | C11: Alimentation | D11: Boulangerie
A12: 46119 | B12: -9.03 | C12: Loisirs | D12: Livre
A13: 46120 | B13: -24.99 | C13: Logement | D13: Internet box
A14: 46120 | B14: -9.84 | C14: Loisirs | D14: Escalade
... A42: 46138 | B42: -29.11 | C42: Alimentation | D42: Courses
A43: 46138 | C43: Loisirs | D43: Cinéma
A44: 46138 | B44: -52.7 | C44: Transport | D44: Essence
A45: 46138 | B45: -9.1 | C45: Loisirs | D45: Escalade
A46: 46140 | B46: -1.8 | C46: Alimentation | D46: Café

Sheet Octobre2026
A1: Date | B1: Montant | C1: Type de Depense | D1: Libelle | F1: Budget restant | G1: Budget initial
B2: -395 | C2: Logement | D2: Loyer | F2: =G2+SUM(B2:B200) -> 2051.32 | G2: 1861.04
B3: =-(250-80-25) -> -145 | C3: Alimentation | D3: Courses du mois
A4: 46293 | B4: 1110 | C4: Revenu | D4: Salaire alternance
A5: 46297 | B5: -1.7 | C5: Transport | D5: Ticket bus
A6: 46297 | B6: -1.8 | C6: Alimentation | D6: Café
A7: 46300 | B7: 182 | C7: Revenu | D7: APL
A8: 46300 | B8: -44.28 | C8: Alimentation | D8: Courses
A9: 46301 | B9: -1.7 | C9: Alimentation | D9: café
A10: 46302 | B10: -28.14 | C10: Loisirs | D10: Restaurant
A11: 46302 | B11: -26.01 | C11: Alimentation | D11: Courses
A12: 46303 | B12: -24.99 | C12: Logement | D12: Internet box
A13: 46303 | B13: -20.29 | C13: Loisirs | D13: Restaurant
A14: 46303 | B14: -27.45 | C14: Loisirs | D14: Restaurant
A15: 46304 | B15: -20.63 | C15: Alimentation | D15: Courses
... A46: 46322 | B46: -2.8 | C46: Alimentation | D46: Café

Sheet Synthèse
A1: Mois | B1: Budget restant
A2: Novembre2025 | B2: =Novembre2025!F2 -> 793.68
A3: Decembre2025 | B3: =Decembre2025!F2 -> 1342.61
A4: Janvier2026 | B4: =Janvier2026!F2 -> 1576.3
A5: Fevrier2026 | B5: =Fevrier2026!F2 -> 1857.81
A6: Mars2026 | B6: =Mars2026!F2 -> 1769.75
A7: Avril2026 | B7: =Avril2026!F2 -> 1861.04
A8: Octobre2026 | B8: =Octobre2026!F2 -> 2051.32
